github_traffic_stats.py
github_traffic_stats2-20.6.6.dist-info/LICENSE
github_traffic_stats2-20.6.6.dist-info/METADATA
github_traffic_stats2-20.6.6.dist-info/WHEEL
github_traffic_stats2-20.6.6.dist-info/entry_points.txt
github_traffic_stats2-20.6.6.dist-info/top_level.txt
github_traffic_stats2-20.6.6.dist-info/RECORD
