Metadata-Version: 2.1
Name: github-traffic-stats2
Version: 20.6.6
Summary: A project to pull and store traffic stats for GitHub projects using GitHub API
Home-page: https://github.com/seladb/github-traffic-stats
Author: seladb
Author-email: pcapplusplus@gmail.com
License: UNKNOWN
Download-URL: https://github.com/seladb/github-traffic-stats/archive/master.tar.gz
Keywords: github,github-traffic,github-api
Platform: UNKNOWN
Classifier: Programming Language :: Python :: 3
Classifier: License :: OSI Approved :: MIT License
Classifier: Operating System :: OS Independent
Requires-Python: >=3
Requires-Dist: githubpy
Requires-Dist: pickledb
Requires-Dist: simplejson
